dxl2/__init__.py
dxl2/response.py
dxl2/v1.py
dxl2/v2.py
dynamixel_python-0.0.6.dist-info/LICENSE
dynamixel_python-0.0.6.dist-info/METADATA
dynamixel_python-0.0.6.dist-info/WHEEL
dynamixel_python-0.0.6.dist-info/top_level.txt
dynamixel_python-0.0.6.dist-info/RECORD
