Metadata-Version: 2.1
Name: dynamixel-python
Version: 0.0.6
Summary: A simple library for communicating with Dynamixel motors
Author-email: Chanhyuk Jung <seagullcjung@gmail.com>
License: MIT
Classifier: Programming Language :: Python :: 3.8
Classifier: Development Status :: 4 - Beta
Classifier: License :: OSI Approved :: MIT License
Requires-Python: >=3.8
License-File: LICENSE
Requires-Dist: pyserial
Requires-Dist: tqdm
Provides-Extra: test
Requires-Dist: pytest ; extra == 'test'
Requires-Dist: pytest-mock ; extra == 'test'
Requires-Dist: mypy ; extra == 'test'
Requires-Dist: mock-serial ; (sys_platform != "win32") and extra == 'test'
